{
  "annotations": {
    "list": [
      {
        "builtIn": 1,
        "datasource": {
          "type": "grafana",
          "uid": "-- Grafana --"
        },
        "enable": true,
        "hide": true,
        "iconColor": "rgba(0, 211, 255, 1)",
        "name": "Annotations & Alerts",
        "type": "dashboard"
      }
    ]
  },
  "editable": true,
  "fiscalYearStartMonth": 0,
  "graphTooltip": 0,
  "links": [],
  "panels": [
    {
      "datasource": {
        "type": "prometheus",
        "uid": "Prometheus"
      },
      "fieldConfig": {
        "defaults": {
          "color": {
            "mode": "thresholds"
          },
          "mappings": [],
          "thresholds": {
            "mode": "absolute",
            "steps": [
              {
                "color": "green",
                "value": 0
              },
              {
                "color": "red",
                "value": 1
              }
            ]
          },
          "unit": "none"
        },
        "overrides": []
      },
      "gridPos": {
        "h": 4,
        "w": 6,
        "x": 0,
        "y": 0
      },
      "id": 1,
      "options": {
        "colorMode": "value",
        "graphMode": "area",
        "justifyMode": "auto",
        "orientation": "auto",
        "percentChangeColorMode": "standard",
        "reduceOptions": {
          "calcs": [
            "lastNotNull"
          ],
          "fields": "",
          "values": false
        },
        "showPercentChange": false,
        "textMode": "auto",
        "wideLayout": true
      },
      "pluginVersion": "12.4.2",
      "targets": [
        {
          "expr": "count(ALERTS{alertstate=\"firing\"}) OR vector(0)",
          "refId": "A"
        }
      ],
      "title": "当前告警数量",
      "type": "stat"
    },
    {
      "datasource": {
        "type": "prometheus",
        "uid": "Prometheus"
      },
      "fieldConfig": {
        "defaults": {
          "color": {
            "mode": "thresholds"
          },
          "mappings": [],
          "thresholds": {
            "mode": "absolute",
            "steps": [
              {
                "color": "green",
                "value": 0
              },
              {
                "color": "orange",
                "value": 1
              }
            ]
          },
          "unit": "none"
        },
        "overrides": []
      },
      "gridPos": {
        "h": 4,
        "w": 6,
        "x": 6,
        "y": 0
      },
      "id": 2,
      "options": {
        "colorMode": "value",
        "graphMode": "area",
        "justifyMode": "auto",
        "orientation": "auto",
        "percentChangeColorMode": "standard",
        "reduceOptions": {
          "calcs": [
            "lastNotNull"
          ],
          "fields": "",
          "values": false
        },
        "showPercentChange": false,
        "textMode": "auto",
        "wideLayout": true
      },
      "pluginVersion": "12.4.2",
      "targets": [
        {
          "expr": "count(count by (container) (ALERTS{alertstate=\"firing\"})) OR vector(0)",
          "refId": "A"
        }
      ],
      "title": "异常容器数量",
      "type": "stat"
    },
    {
      "datasource": {
        "type": "prometheus",
        "uid": "Prometheus"
      },
      "fieldConfig": {
        "defaults": {
          "color": {
            "mode": "continuous-BlYlRd"
          },
          "mappings": [],
          "thresholds": {
            "mode": "absolute",
            "steps": [
              {
                "color": "green",
                "value": 0
              },
              {
                "color": "red",
                "value": 80
              }
            ]
          },
          "unit": "short"
        },
        "overrides": []
      },
      "gridPos": {
        "h": 4,
        "w": 6,
        "x": 12,
        "y": 0
      },
      "id": 3,
      "options": {
        "colorMode": "value",
        "graphMode": "area",
        "justifyMode": "auto",
        "orientation": "auto",
        "percentChangeColorMode": "standard",
        "reduceOptions": {
          "calcs": [
            "lastNotNull"
          ],
          "fields": "",
          "values": false
        },
        "showPercentChange": false,
        "textMode": "name",
        "wideLayout": true
      },
      "pluginVersion": "12.4.2",
      "targets": [
        {
          "expr": "topk(1, rate(container_cpu_usage_usec[1m]))",
          "legendFormat": "{{container}}",
          "refId": "A"
        }
      ],
      "title": "当前负载最高容器",
      "type": "stat"
    },
    {
      "datasource": {
        "type": "prometheus",
        "uid": "Prometheus"
      },
      "fieldConfig": {
        "defaults": {
          "color": {
            "mode": "thresholds"
          },
          "mappings": [],
          "thresholds": {
            "mode": "absolute",
            "steps": [
              {
                "color": "green",
                "value": 0
              }
            ]
          },
          "unit": "none"
        },
        "overrides": []
      },
      "gridPos": {
        "h": 4,
        "w": 6,
        "x": 18,
        "y": 0
      },
      "id": 4,
      "options": {
        "colorMode": "value",
        "graphMode": "none",
        "justifyMode": "auto",
        "orientation": "auto",
        "percentChangeColorMode": "standard",
        "reduceOptions": {
          "calcs": [
            "lastNotNull"
          ],
          "fields": "",
          "values": false
        },
        "showPercentChange": false,
        "textMode": "value",
        "wideLayout": true
      },
      "pluginVersion": "12.4.2",
      "targets": [
        {
          "editorMode": "code",
          "expr": "vector(10)",
          "range": true,
          "refId": "A"
        }
      ],
      "title": "当前启用的监测项数量",
      "type": "stat"
    },
    {
      "collapsed": true,
      "gridPos": {
        "h": 1,
        "w": 24,
        "x": 0,
        "y": 4
      },
      "id": 100,
      "panels": [
        {
          "datasource": {
            "type": "prometheus",
            "uid": "Prometheus"
          },
          "fieldConfig": {
            "defaults": {
              "color": {
                "mode": "palette-classic"
              },
              "custom": {
                "axisBorderShow": false,
                "axisCenteredZero": false,
                "axisColorMode": "text",
                "axisLabel": "",
                "axisPlacement": "auto",
                "barAlignment": 0,
                "barWidthFactor": 0.6,
                "drawStyle": "line",
                "fillOpacity": 10,
                "gradientMode": "opacity",
                "hideFrom": {
                  "legend": false,
                  "tooltip": false,
                  "viz": false
                },
                "insertNulls": false,
                "lineInterpolation": "linear",
                "lineWidth": 2,
                "pointSize": 3,
                "scaleDistribution": {
                  "type": "linear"
                },
                "showPoints": "never",
                "showValues": false,
                "spanNulls": false,
                "stacking": {
                  "group": "A",
                  "mode": "none"
                },
                "thresholdsStyle": {
                  "mode": "off"
                }
              },
              "mappings": [],
              "thresholds": {
                "mode": "absolute",
                "steps": [
                  {
                    "color": "green",
                    "value": 0
                  },
                  {
                    "color": "red",
                    "value": 80
                  }
                ]
              },
              "unit": "short"
            },
            "overrides": [
              {
                "matcher": {
                  "id": "byRegexp",
                  "options": ".*web.*"
                },
                "properties": [
                  {
                    "id": "color",
                    "value": {
                      "fixedColor": "#4C8BF5",
                      "mode": "fixed"
                    }
                  }
                ]
              },
              {
                "matcher": {
                  "id": "byRegexp",
                  "options": ".*cache_db.*"
                },
                "properties": [
                  {
                    "id": "color",
                    "value": {
                      "fixedColor": "#2ECC71",
                      "mode": "fixed"
                    }
                  }
                ]
              }
            ]
          },
          "gridPos": {
            "h": 7,
            "w": 12,
            "x": 0,
            "y": 5
          },
          "id": 5,
          "options": {
            "legend": {
              "calcs": [],
              "displayMode": "list",
              "placement": "bottom",
              "showLegend": true
            },
            "tooltip": {
              "hideZeros": false,
              "mode": "multi",
              "sort": "none"
            }
          },
          "pluginVersion": "12.4.2",
          "targets": [
            {
              "expr": "rate(container_cpu_usage_usec[1m])",
              "legendFormat": "{{container}} ({{container_role}})",
              "refId": "A"
            }
          ],
          "title": "各容器 CPU 使用情况",
          "type": "timeseries"
        },
        {
          "datasource": {
            "type": "prometheus",
            "uid": "Prometheus"
          },
          "fieldConfig": {
            "defaults": {
              "color": {
                "mode": "palette-classic"
              },
              "custom": {
                "axisBorderShow": false,
                "axisCenteredZero": false,
                "axisColorMode": "text",
                "axisLabel": "",
                "axisPlacement": "auto",
                "barAlignment": 0,
                "barWidthFactor": 0.6,
                "drawStyle": "line",
                "fillOpacity": 10,
                "gradientMode": "opacity",
                "hideFrom": {
                  "legend": false,
                  "tooltip": false,
                  "viz": false
                },
                "insertNulls": false,
                "lineInterpolation": "linear",
                "lineWidth": 2,
                "pointSize": 3,
                "scaleDistribution": {
                  "type": "linear"
                },
                "showPoints": "never",
                "showValues": false,
                "spanNulls": false,
                "stacking": {
                  "group": "A",
                  "mode": "none"
                },
                "thresholdsStyle": {
                  "mode": "off"
                }
              },
              "mappings": [],
              "thresholds": {
                "mode": "absolute",
                "steps": [
                  {
                    "color": "green",
                    "value": 0
                  },
                  {
                    "color": "red",
                    "value": 80
                  }
                ]
              },
              "unit": "bytes"
            },
            "overrides": [
              {
                "matcher": {
                  "id": "byRegexp",
                  "options": ".*web.*"
                },
                "properties": [
                  {
                    "id": "color",
                    "value": {
                      "fixedColor": "#4C8BF5",
                      "mode": "fixed"
                    }
                  }
                ]
              },
              {
                "matcher": {
                  "id": "byRegexp",
                  "options": ".*cache_db.*"
                },
                "properties": [
                  {
                    "id": "color",
                    "value": {
                      "fixedColor": "#2ECC71",
                      "mode": "fixed"
                    }
                  }
                ]
              }
            ]
          },
          "gridPos": {
            "h": 7,
            "w": 12,
            "x": 12,
            "y": 5
          },
          "id": 6,
          "options": {
            "legend": {
              "calcs": [],
              "displayMode": "list",
              "placement": "bottom",
              "showLegend": true
            },
            "tooltip": {
              "hideZeros": false,
              "mode": "multi",
              "sort": "none"
            }
          },
          "pluginVersion": "12.4.2",
          "targets": [
            {
              "expr": "container_memory_current_bytes",
              "legendFormat": "{{container}} ({{container_role}})",
              "refId": "A"
            }
          ],
          "title": "各容器当前内存占用",
          "type": "timeseries"
        },
        {
          "datasource": {
            "type": "prometheus",
            "uid": "Prometheus"
          },
          "description": "反映容器内任务在单位时间内发生切换的频繁程度，可用于观察容器运行活跃度。",
          "fieldConfig": {
            "defaults": {
              "color": {
                "mode": "palette-classic"
              },
              "custom": {
                "axisBorderShow": false,
                "axisCenteredZero": false,
                "axisColorMode": "text",
                "axisLabel": "",
                "axisPlacement": "auto",
                "barAlignment": 0,
                "barWidthFactor": 0.6,
                "drawStyle": "line",
                "fillOpacity": 10,
                "gradientMode": "opacity",
                "hideFrom": {
                  "legend": false,
                  "tooltip": false,
                  "viz": false
                },
                "insertNulls": false,
                "lineInterpolation": "linear",
                "lineWidth": 2,
                "pointSize": 3,
                "scaleDistribution": {
                  "type": "linear"
                },
                "showPoints": "never",
                "showValues": false,
                "spanNulls": false,
                "stacking": {
                  "group": "A",
                  "mode": "none"
                },
                "thresholdsStyle": {
                  "mode": "off"
                }
              },
              "mappings": [],
              "thresholds": {
                "mode": "absolute",
                "steps": [
                  {
                    "color": "green",
                    "value": 0
                  },
                  {
                    "color": "red",
                    "value": 80
                  }
                ]
              },
              "unit": "ops"
            },
            "overrides": [
              {
                "matcher": {
                  "id": "byRegexp",
                  "options": ".*web.*"
                },
                "properties": [
                  {
                    "id": "color",
                    "value": {
                      "fixedColor": "#4C8BF5",
                      "mode": "fixed"
                    }
                  }
                ]
              },
              {
                "matcher": {
                  "id": "byRegexp",
                  "options": ".*cache_db.*"
                },
                "properties": [
                  {
                    "id": "color",
                    "value": {
                      "fixedColor": "#2ECC71",
                      "mode": "fixed"
                    }
                  }
                ]
              }
            ]
          },
          "gridPos": {
            "h": 7,
            "w": 12,
            "x": 0,
            "y": 40
          },
          "id": 7,
          "options": {
            "legend": {
              "calcs": [],
              "displayMode": "list",
              "placement": "bottom",
              "showLegend": true
            },
            "tooltip": {
              "hideZeros": false,
              "mode": "multi",
              "sort": "none"
            }
          },
          "pluginVersion": "12.4.2",
          "targets": [
            {
              "expr": "rate(container_sched_switch_total[1m])",
              "legendFormat": "{{container}} ({{container_role}})",
              "refId": "A"
            }
          ],
          "title": "各容器线程切换频率",
          "type": "timeseries"
        },
        {
          "datasource": {
            "type": "prometheus",
            "uid": "Prometheus"
          },
          "description": "反映容器内任务在单位时间内被唤醒的频繁程度，可用于观察请求波动和事件活跃情况。",
          "fieldConfig": {
            "defaults": {
              "color": {
                "mode": "palette-classic"
              },
              "custom": {
                "axisBorderShow": false,
                "axisCenteredZero": false,
                "axisColorMode": "text",
                "axisLabel": "",
                "axisPlacement": "auto",
                "barAlignment": 0,
                "barWidthFactor": 0.6,
                "drawStyle": "line",
                "fillOpacity": 10,
                "gradientMode": "opacity",
                "hideFrom": {
                  "legend": false,
                  "tooltip": false,
                  "viz": false
                },
                "insertNulls": false,
                "lineInterpolation": "linear",
                "lineWidth": 2,
                "pointSize": 3,
                "scaleDistribution": {
                  "type": "linear"
                },
                "showPoints": "never",
                "showValues": false,
                "spanNulls": false,
                "stacking": {
                  "group": "A",
                  "mode": "none"
                },
                "thresholdsStyle": {
                  "mode": "off"
                }
              },
              "mappings": [],
              "thresholds": {
                "mode": "absolute",
                "steps": [
                  {
                    "color": "green",
                    "value": 0
                  },
                  {
                    "color": "red",
                    "value": 80
                  }
                ]
              },
              "unit": "ops"
            },
            "overrides": [
              {
                "matcher": {
                  "id": "byRegexp",
                  "options": ".*web.*"
                },
                "properties": [
                  {
                    "id": "color",
                    "value": {
                      "fixedColor": "#4C8BF5",
                      "mode": "fixed"
                    }
                  }
                ]
              },
              {
                "matcher": {
                  "id": "byRegexp",
                  "options": ".*cache_db.*"
                },
                "properties": [
                  {
                    "id": "color",
                    "value": {
                      "fixedColor": "#2ECC71",
                      "mode": "fixed"
                    }
                  }
                ]
              }
            ]
          },
          "gridPos": {
            "h": 7,
            "w": 12,
            "x": 12,
            "y": 40
          },
          "id": 8,
          "options": {
            "legend": {
              "calcs": [],
              "displayMode": "list",
              "placement": "bottom",
              "showLegend": true
            },
            "tooltip": {
              "hideZeros": false,
              "mode": "multi",
              "sort": "none"
            }
          },
          "pluginVersion": "12.4.2",
          "targets": [
            {
              "expr": "rate(container_sched_wakeup_total[1m])",
              "legendFormat": "{{container}} ({{container_role}})",
              "refId": "A"
            }
          ],
          "title": "各容器线程唤醒频率",
          "type": "timeseries"
        },
        {
          "datasource": {
            "type": "prometheus",
            "uid": "Prometheus"
          },
          "description": "反映最近窗口内任务等待 CPU 的平均耗时，可用于判断容器是否存在明显资源竞争。",
          "fieldConfig": {
            "defaults": {
              "color": {
                "mode": "palette-classic"
              },
              "custom": {
                "axisBorderShow": false,
                "axisCenteredZero": false,
                "axisColorMode": "text",
                "axisLabel": "",
                "axisPlacement": "auto",
                "barAlignment": 0,
                "barWidthFactor": 0.6,
                "drawStyle": "line",
                "fillOpacity": 10,
                "gradientMode": "opacity",
                "hideFrom": {
                  "legend": false,
                  "tooltip": false,
                  "viz": false
                },
                "insertNulls": false,
                "lineInterpolation": "linear",
                "lineWidth": 2,
                "pointSize": 3,
                "scaleDistribution": {
                  "type": "linear"
                },
                "showPoints": "never",
                "showValues": false,
                "spanNulls": false,
                "stacking": {
                  "group": "A",
                  "mode": "none"
                },
                "thresholdsStyle": {
                  "mode": "off"
                }
              },
              "mappings": [],
              "thresholds": {
                "mode": "absolute",
                "steps": [
                  {
                    "color": "green",
                    "value": 0
                  },
                  {
                    "color": "red",
                    "value": 80
                  }
                ]
              },
              "unit": "µs"
            },
            "overrides": [
              {
                "matcher": {
                  "id": "byRegexp",
                  "options": ".*web.*"
                },
                "properties": [
                  {
                    "id": "color",
                    "value": {
                      "fixedColor": "#4C8BF5",
                      "mode": "fixed"
                    }
                  }
                ]
              },
              {
                "matcher": {
                  "id": "byRegexp",
                  "options": ".*cache_db.*"
                },
                "properties": [
                  {
                    "id": "color",
                    "value": {
                      "fixedColor": "#2ECC71",
                      "mode": "fixed"
                    }
                  }
                ]
              }
            ]
          },
          "gridPos": {
            "h": 7,
            "w": 12,
            "x": 0,
            "y": 47
          },
          "id": 9,
          "options": {
            "legend": {
              "calcs": [],
              "displayMode": "list",
              "placement": "bottom",
              "showLegend": true
            },
            "tooltip": {
              "hideZeros": false,
              "mode": "multi",
              "sort": "none"
            }
          },
          "pluginVersion": "12.4.2",
          "targets": [
            {
              "expr": "container_sched_latency_avg_us",
              "legendFormat": "{{container}} ({{container_role}})",
              "refId": "A"
            }
          ],
          "title": "各容器平均调度延迟",
          "type": "timeseries"
        },
        {
          "datasource": {
            "type": "prometheus",
            "uid": "Prometheus"
          },
          "description": "反映最近窗口内任务等待 CPU 的最大耗时，可用于发现短时卡顿和抖动。",
          "fieldConfig": {
            "defaults": {
              "color": {
                "mode": "palette-classic"
              },
              "custom": {
                "axisBorderShow": false,
                "axisCenteredZero": false,
                "axisColorMode": "text",
                "axisLabel": "",
                "axisPlacement": "auto",
                "barAlignment": 0,
                "barWidthFactor": 0.6,
                "drawStyle": "line",
                "fillOpacity": 10,
                "gradientMode": "opacity",
                "hideFrom": {
                  "legend": false,
                  "tooltip": false,
                  "viz": false
                },
                "insertNulls": false,
                "lineInterpolation": "linear",
                "lineWidth": 2,
                "pointSize": 3,
                "scaleDistribution": {
                  "type": "linear"
                },
                "showPoints": "never",
                "showValues": false,
                "spanNulls": false,
                "stacking": {
                  "group": "A",
                  "mode": "none"
                },
                "thresholdsStyle": {
                  "mode": "off"
                }
              },
              "mappings": [],
              "thresholds": {
                "mode": "absolute",
                "steps": [
                  {
                    "color": "green",
                    "value": 0
                  },
                  {
                    "color": "red",
                    "value": 80
                  }
                ]
              },
              "unit": "µs"
            },
            "overrides": [
              {
                "matcher": {
                  "id": "byRegexp",
                  "options": ".*web.*"
                },
                "properties": [
                  {
                    "id": "color",
                    "value": {
                      "fixedColor": "#4C8BF5",
                      "mode": "fixed"
                    }
                  }
                ]
              },
              {
                "matcher": {
                  "id": "byRegexp",
                  "options": ".*cache_db.*"
                },
                "properties": [
                  {
                    "id": "color",
                    "value": {
                      "fixedColor": "#2ECC71",
                      "mode": "fixed"
                    }
                  }
                ]
              }
            ]
          },
          "gridPos": {
            "h": 7,
            "w": 12,
            "x": 12,
            "y": 47
          },
          "id": 10,
          "options": {
            "legend": {
              "calcs": [],
              "displayMode": "list",
              "placement": "bottom",
              "showLegend": true
            },
            "tooltip": {
              "hideZeros": false,
              "mode": "multi",
              "sort": "none"
            }
          },
          "pluginVersion": "12.4.2",
          "targets": [
            {
              "expr": "container_sched_latency_max_us",
              "legendFormat": "{{container}} ({{container_role}})",
              "refId": "A"
            }
          ],
          "title": "各容器最大调度延迟",
          "type": "timeseries"
        }
      ],
      "title": "全局概览",
      "type": "row"
    },
    {
      "collapsed": true,
      "gridPos": {
        "h": 1,
        "w": 24,
        "x": 0,
        "y": 5
      },
      "id": 101,
      "panels": [
        {
          "datasource": {
            "type": "prometheus",
            "uid": "Prometheus"
          },
          "fieldConfig": {
            "defaults": {
              "color": {
                "mode": "palette-classic"
              },
              "custom": {
                "axisBorderShow": false,
                "axisCenteredZero": false,
                "axisColorMode": "text",
                "axisLabel": "",
                "axisPlacement": "auto",
                "barAlignment": 0,
                "barWidthFactor": 0.6,
                "drawStyle": "line",
                "fillOpacity": 10,
                "gradientMode": "opacity",
                "hideFrom": {
                  "legend": false,
                  "tooltip": false,
                  "viz": false
                },
                "insertNulls": false,
                "lineInterpolation": "linear",
                "lineWidth": 2,
                "pointSize": 5,
                "scaleDistribution": {
                  "type": "linear"
                },
                "showPoints": "never",
                "showValues": false,
                "spanNulls": false,
                "stacking": {
                  "group": "A",
                  "mode": "none"
                },
                "thresholdsStyle": {
                  "mode": "off"
                }
              },
              "mappings": [],
              "thresholds": {
                "mode": "absolute",
                "steps": [
                  {
                    "color": "green",
                    "value": 0
                  },
                  {
                    "color": "red",
                    "value": 80
                  }
                ]
              },
              "unit": "short"
            },
            "overrides": [
              {
                "matcher": {
                  "id": "byRegexp",
                  "options": ".*web.*"
                },
                "properties": [
                  {
                    "id": "color",
                    "value": {
                      "fixedColor": "#4C8BF5",
                      "mode": "fixed"
                    }
                  }
                ]
              },
              {
                "matcher": {
                  "id": "byRegexp",
                  "options": ".*cache_db.*"
                },
                "properties": [
                  {
                    "id": "color",
                    "value": {
                      "fixedColor": "#2ECC71",
                      "mode": "fixed"
                    }
                  }
                ]
              }
            ]
          },
          "gridPos": {
            "h": 7,
            "w": 8,
            "x": 0,
            "y": 244
          },
          "id": 11,
          "options": {
            "legend": {
              "calcs": [],
              "displayMode": "list",
              "placement": "bottom",
              "showLegend": true
            },
            "tooltip": {
              "hideZeros": false,
              "mode": "multi",
              "sort": "none"
            }
          },
          "pluginVersion": "12.4.2",
          "targets": [
            {
              "expr": "rate(container_cpu_usage_usec{container_role=\"web\"}[1m])",
              "legendFormat": "{{container}} ({{container_role}})",
              "refId": "A"
            }
          ],
          "title": "Web 类容器 CPU 使用情况",
          "type": "timeseries"
        },
        {
          "datasource": {
            "type": "prometheus",
            "uid": "Prometheus"
          },
          "fieldConfig": {
            "defaults": {
              "color": {
                "mode": "palette-classic"
              },
              "custom": {
                "axisBorderShow": false,
                "axisCenteredZero": false,
                "axisColorMode": "text",
                "axisLabel": "",
                "axisPlacement": "auto",
                "barAlignment": 0,
                "barWidthFactor": 0.6,
                "drawStyle": "line",
                "fillOpacity": 10,
                "gradientMode": "opacity",
                "hideFrom": {
                  "legend": false,
                  "tooltip": false,
                  "viz": false
                },
                "insertNulls": false,
                "lineInterpolation": "linear",
                "lineWidth": 2,
                "pointSize": 5,
                "scaleDistribution": {
                  "type": "linear"
                },
                "showPoints": "never",
                "showValues": false,
                "spanNulls": false,
                "stacking": {
                  "group": "A",
                  "mode": "none"
                },
                "thresholdsStyle": {
                  "mode": "off"
                }
              },
              "mappings": [],
              "thresholds": {
                "mode": "absolute",
                "steps": [
                  {
                    "color": "green",
                    "value": 0
                  },
                  {
                    "color": "red",
                    "value": 80
                  }
                ]
              },
              "unit": "ops"
            },
            "overrides": [
              {
                "matcher": {
                  "id": "byRegexp",
                  "options": ".*web.*"
                },
                "properties": [
                  {
                    "id": "color",
                    "value": {
                      "fixedColor": "#4C8BF5",
                      "mode": "fixed"
                    }
                  }
                ]
              },
              {
                "matcher": {
                  "id": "byRegexp",
                  "options": ".*cache_db.*"
                },
                "properties": [
                  {
                    "id": "color",
                    "value": {
                      "fixedColor": "#2ECC71",
                      "mode": "fixed"
                    }
                  }
                ]
              }
            ]
          },
          "gridPos": {
            "h": 7,
            "w": 8,
            "x": 8,
            "y": 244
          },
          "id": 12,
          "options": {
            "legend": {
              "calcs": [],
              "displayMode": "list",
              "placement": "bottom",
              "showLegend": true
            },
            "tooltip": {
              "hideZeros": false,
              "mode": "multi",
              "sort": "none"
            }
          },
          "pluginVersion": "12.4.2",
          "targets": [
            {
              "expr": "rate(container_sched_switch_total{container_role=\"web\"}[1m])",
              "legendFormat": "{{container}} ({{container_role}})",
              "refId": "A"
            }
          ],
          "title": "Web 类容器线程切换频率",
          "type": "timeseries"
        },
        {
          "datasource": {
            "type": "prometheus",
            "uid": "Prometheus"
          },
          "fieldConfig": {
            "defaults": {
              "color": {
                "mode": "palette-classic"
              },
              "custom": {
                "axisBorderShow": false,
                "axisCenteredZero": false,
                "axisColorMode": "text",
                "axisLabel": "",
                "axisPlacement": "auto",
                "barAlignment": 0,
                "barWidthFactor": 0.6,
                "drawStyle": "line",
                "fillOpacity": 10,
                "gradientMode": "opacity",
                "hideFrom": {
                  "legend": false,
                  "tooltip": false,
                  "viz": false
                },
                "insertNulls": false,
                "lineInterpolation": "linear",
                "lineWidth": 2,
                "pointSize": 5,
                "scaleDistribution": {
                  "type": "linear"
                },
                "showPoints": "never",
                "showValues": false,
                "spanNulls": false,
                "stacking": {
                  "group": "A",
                  "mode": "none"
                },
                "thresholdsStyle": {
                  "mode": "off"
                }
              },
              "mappings": [],
              "thresholds": {
                "mode": "absolute",
                "steps": [
                  {
                    "color": "green",
                    "value": 0
                  },
                  {
                    "color": "red",
                    "value": 80
                  }
                ]
              },
              "unit": "µs"
            },
            "overrides": [
              {
                "matcher": {
                  "id": "byRegexp",
                  "options": ".*web.*"
                },
                "properties": [
                  {
                    "id": "color",
                    "value": {
                      "fixedColor": "#4C8BF5",
                      "mode": "fixed"
                    }
                  }
                ]
              },
              {
                "matcher": {
                  "id": "byRegexp",
                  "options": ".*cache_db.*"
                },
                "properties": [
                  {
                    "id": "color",
                    "value": {
                      "fixedColor": "#2ECC71",
                      "mode": "fixed"
                    }
                  }
                ]
              }
            ]
          },
          "gridPos": {
            "h": 7,
            "w": 8,
            "x": 16,
            "y": 244
          },
          "id": 13,
          "options": {
            "legend": {
              "calcs": [],
              "displayMode": "list",
              "placement": "bottom",
              "showLegend": true
            },
            "tooltip": {
              "hideZeros": false,
              "mode": "multi",
              "sort": "none"
            }
          },
          "pluginVersion": "12.4.2",
          "targets": [
            {
              "expr": "container_sched_latency_last_us{container_role=\"web\"}",
              "legendFormat": "{{container}} ({{container_role}})",
              "refId": "A"
            }
          ],
          "title": "Web 类容器最近一次等待 CPU 时间",
          "type": "timeseries"
        }
      ],
      "title": "Web 类容器专区",
      "type": "row"
    },
    {
      "collapsed": true,
      "gridPos": {
        "h": 1,
        "w": 24,
        "x": 0,
        "y": 6
      },
      "id": 102,
      "panels": [
        {
          "datasource": {
            "type": "prometheus",
            "uid": "Prometheus"
          },
          "fieldConfig": {
            "defaults": {
              "color": {
                "mode": "palette-classic"
              },
              "custom": {
                "axisBorderShow": false,
                "axisCenteredZero": false,
                "axisColorMode": "text",
                "axisLabel": "",
                "axisPlacement": "auto",
                "barAlignment": 0,
                "barWidthFactor": 0.6,
                "drawStyle": "line",
                "fillOpacity": 10,
                "gradientMode": "opacity",
                "hideFrom": {
                  "legend": false,
                  "tooltip": false,
                  "viz": false
                },
                "insertNulls": false,
                "lineInterpolation": "linear",
                "lineWidth": 2,
                "pointSize": 5,
                "scaleDistribution": {
                  "type": "linear"
                },
                "showPoints": "never",
                "showValues": false,
                "spanNulls": false,
                "stacking": {
                  "group": "A",
                  "mode": "none"
                },
                "thresholdsStyle": {
                  "mode": "off"
                }
              },
              "mappings": [],
              "thresholds": {
                "mode": "absolute",
                "steps": [
                  {
                    "color": "green",
                    "value": 0
                  },
                  {
                    "color": "red",
                    "value": 80
                  }
                ]
              },
              "unit": "short"
            },
            "overrides": [
              {
                "matcher": {
                  "id": "byRegexp",
                  "options": ".*web.*"
                },
                "properties": [
                  {
                    "id": "color",
                    "value": {
                      "fixedColor": "#4C8BF5",
                      "mode": "fixed"
                    }
                  }
                ]
              },
              {
                "matcher": {
                  "id": "byRegexp",
                  "options": ".*cache_db.*"
                },
                "properties": [
                  {
                    "id": "color",
                    "value": {
                      "fixedColor": "#2ECC71",
                      "mode": "fixed"
                    }
                  }
                ]
              }
            ]
          },
          "gridPos": {
            "h": 7,
            "w": 8,
            "x": 0,
            "y": 245
          },
          "id": 14,
          "options": {
            "legend": {
              "calcs": [],
              "displayMode": "list",
              "placement": "bottom",
              "showLegend": true
            },
            "tooltip": {
              "hideZeros": false,
              "mode": "multi",
              "sort": "none"
            }
          },
          "pluginVersion": "12.4.2",
          "targets": [
            {
              "expr": "rate(container_cpu_usage_usec{container_role=\"cache_db\"}[1m])",
              "legendFormat": "{{container}} ({{container_role}})",
              "refId": "A"
            }
          ],
          "title": "缓存/数据库类容器 CPU 使用情况",
          "type": "timeseries"
        },
        {
          "datasource": {
            "type": "prometheus",
            "uid": "Prometheus"
          },
          "fieldConfig": {
            "defaults": {
              "color": {
                "mode": "palette-classic"
              },
              "custom": {
                "axisBorderShow": false,
                "axisCenteredZero": false,
                "axisColorMode": "text",
                "axisLabel": "",
                "axisPlacement": "auto",
                "barAlignment": 0,
                "barWidthFactor": 0.6,
                "drawStyle": "line",
                "fillOpacity": 10,
                "gradientMode": "opacity",
                "hideFrom": {
                  "legend": false,
                  "tooltip": false,
                  "viz": false
                },
                "insertNulls": false,
                "lineInterpolation": "linear",
                "lineWidth": 2,
                "pointSize": 5,
                "scaleDistribution": {
                  "type": "linear"
                },
                "showPoints": "never",
                "showValues": false,
                "spanNulls": false,
                "stacking": {
                  "group": "A",
                  "mode": "none"
                },
                "thresholdsStyle": {
                  "mode": "off"
                }
              },
              "mappings": [],
              "thresholds": {
                "mode": "absolute",
                "steps": [
                  {
                    "color": "green",
                    "value": 0
                  },
                  {
                    "color": "red",
                    "value": 80
                  }
                ]
              },
              "unit": "bytes"
            },
            "overrides": [
              {
                "matcher": {
                  "id": "byRegexp",
                  "options": ".*web.*"
                },
                "properties": [
                  {
                    "id": "color",
                    "value": {
                      "fixedColor": "#4C8BF5",
                      "mode": "fixed"
                    }
                  }
                ]
              },
              {
                "matcher": {
                  "id": "byRegexp",
                  "options": ".*cache_db.*"
                },
                "properties": [
                  {
                    "id": "color",
                    "value": {
                      "fixedColor": "#2ECC71",
                      "mode": "fixed"
                    }
                  }
                ]
              }
            ]
          },
          "gridPos": {
            "h": 7,
            "w": 8,
            "x": 8,
            "y": 245
          },
          "id": 15,
          "options": {
            "legend": {
              "calcs": [],
              "displayMode": "list",
              "placement": "bottom",
              "showLegend": true
            },
            "tooltip": {
              "hideZeros": false,
              "mode": "multi",
              "sort": "none"
            }
          },
          "pluginVersion": "12.4.2",
          "targets": [
            {
              "expr": "container_memory_current_bytes{container_role=\"cache_db\"}",
              "legendFormat": "{{container}} ({{container_role}})",
              "refId": "A"
            }
          ],
          "title": "缓存/数据库类容器当前内存占用",
          "type": "timeseries"
        },
        {
          "datasource": {
            "type": "prometheus",
            "uid": "Prometheus"
          },
          "fieldConfig": {
            "defaults": {
              "color": {
                "mode": "palette-classic"
              },
              "custom": {
                "axisBorderShow": false,
                "axisCenteredZero": false,
                "axisColorMode": "text",
                "axisLabel": "",
                "axisPlacement": "auto",
                "barAlignment": 0,
                "barWidthFactor": 0.6,
                "drawStyle": "line",
                "fillOpacity": 10,
                "gradientMode": "opacity",
                "hideFrom": {
                  "legend": false,
                  "tooltip": false,
                  "viz": false
                },
                "insertNulls": false,
                "lineInterpolation": "linear",
                "lineWidth": 2,
                "pointSize": 5,
                "scaleDistribution": {
                  "type": "linear"
                },
                "showPoints": "never",
                "showValues": false,
                "spanNulls": false,
                "stacking": {
                  "group": "A",
                  "mode": "none"
                },
                "thresholdsStyle": {
                  "mode": "off"
                }
              },
              "mappings": [],
              "thresholds": {
                "mode": "absolute",
                "steps": [
                  {
                    "color": "green",
                    "value": 0
                  },
                  {
                    "color": "red",
                    "value": 80
                  }
                ]
              },
              "unit": "µs"
            },
            "overrides": [
              {
                "matcher": {
                  "id": "byRegexp",
                  "options": ".*web.*"
                },
                "properties": [
                  {
                    "id": "color",
                    "value": {
                      "fixedColor": "#4C8BF5",
                      "mode": "fixed"
                    }
                  }
                ]
              },
              {
                "matcher": {
                  "id": "byRegexp",
                  "options": ".*cache_db.*"
                },
                "properties": [
                  {
                    "id": "color",
                    "value": {
                      "fixedColor": "#2ECC71",
                      "mode": "fixed"
                    }
                  }
                ]
              }
            ]
          },
          "gridPos": {
            "h": 7,
            "w": 8,
            "x": 16,
            "y": 245
          },
          "id": 16,
          "options": {
            "legend": {
              "calcs": [],
              "displayMode": "list",
              "placement": "bottom",
              "showLegend": true
            },
            "tooltip": {
              "hideZeros": false,
              "mode": "multi",
              "sort": "none"
            }
          },
          "pluginVersion": "12.4.2",
          "targets": [
            {
              "expr": "container_sched_latency_avg_us{container_role=\"cache_db\"}",
              "legendFormat": "{{container}} ({{container_role}})",
              "refId": "A"
            }
          ],
          "title": "缓存/数据库类容器平均等待 CPU 时间",
          "type": "timeseries"
        },
        {
          "datasource": {
            "type": "prometheus",
            "uid": "Prometheus"
          },
          "fieldConfig": {
            "defaults": {
              "color": {
                "mode": "palette-classic"
              },
              "custom": {
                "axisBorderShow": false,
                "axisCenteredZero": false,
                "axisColorMode": "text",
                "axisLabel": "",
                "axisPlacement": "auto",
                "barAlignment": 0,
                "barWidthFactor": 0.6,
                "drawStyle": "line",
                "fillOpacity": 10,
                "gradientMode": "opacity",
                "hideFrom": {
                  "legend": false,
                  "tooltip": false,
                  "viz": false
                },
                "insertNulls": false,
                "lineInterpolation": "linear",
                "lineWidth": 2,
                "pointSize": 5,
                "scaleDistribution": {
                  "type": "linear"
                },
                "showPoints": "never",
                "showValues": false,
                "spanNulls": false,
                "stacking": {
                  "group": "A",
                  "mode": "none"
                },
                "thresholdsStyle": {
                  "mode": "off"
                }
              },
              "mappings": [],
              "thresholds": {
                "mode": "absolute",
                "steps": [
                  {
                    "color": "green",
                    "value": 0
                  },
                  {
                    "color": "red",
                    "value": 80
                  }
                ]
              },
              "unit": "µs"
            },
            "overrides": [
              {
                "matcher": {
                  "id": "byRegexp",
                  "options": ".*web.*"
                },
                "properties": [
                  {
                    "id": "color",
                    "value": {
                      "fixedColor": "#4C8BF5",
                      "mode": "fixed"
                    }
                  }
                ]
              },
              {
                "matcher": {
                  "id": "byRegexp",
                  "options": ".*cache_db.*"
                },
                "properties": [
                  {
                    "id": "color",
                    "value": {
                      "fixedColor": "#2ECC71",
                      "mode": "fixed"
                    }
                  }
                ]
              }
            ]
          },
          "gridPos": {
            "h": 7,
            "w": 12,
            "x": 0,
            "y": 252
          },
          "id": 17,
          "options": {
            "legend": {
              "calcs": [],
              "displayMode": "list",
              "placement": "bottom",
              "showLegend": true
            },
            "tooltip": {
              "hideZeros": false,
              "mode": "multi",
              "sort": "none"
            }
          },
          "pluginVersion": "12.4.2",
          "targets": [
            {
              "expr": "container_sched_latency_max_us{container_role=\"cache_db\"}",
              "legendFormat": "{{container}} ({{container_role}})",
              "refId": "A"
            }
          ],
          "title": "缓存/数据库类容器最大卡顿时间",
          "type": "timeseries"
        },
        {
          "datasource": {
            "type": "prometheus",
            "uid": "Prometheus"
          },
          "fieldConfig": {
            "defaults": {
              "color": {
                "mode": "palette-classic"
              },
              "custom": {
                "axisBorderShow": false,
                "axisCenteredZero": false,
                "axisColorMode": "text",
                "axisLabel": "",
                "axisPlacement": "auto",
                "barAlignment": 0,
                "barWidthFactor": 0.6,
                "drawStyle": "line",
                "fillOpacity": 10,
                "gradientMode": "opacity",
                "hideFrom": {
                  "legend": false,
                  "tooltip": false,
                  "viz": false
                },
                "insertNulls": false,
                "lineInterpolation": "linear",
                "lineWidth": 2,
                "pointSize": 5,
                "scaleDistribution": {
                  "type": "linear"
                },
                "showPoints": "never",
                "showValues": false,
                "spanNulls": false,
                "stacking": {
                  "group": "A",
                  "mode": "none"
                },
                "thresholdsStyle": {
                  "mode": "off"
                }
              },
              "mappings": [],
              "thresholds": {
                "mode": "absolute",
                "steps": [
                  {
                    "color": "green",
                    "value": 0
                  },
                  {
                    "color": "red",
                    "value": 80
                  }
                ]
              },
              "unit": "ops"
            },
            "overrides": [
              {
                "matcher": {
                  "id": "byRegexp",
                  "options": ".*web.*"
                },
                "properties": [
                  {
                    "id": "color",
                    "value": {
                      "fixedColor": "#4C8BF5",
                      "mode": "fixed"
                    }
                  }
                ]
              },
              {
                "matcher": {
                  "id": "byRegexp",
                  "options": ".*cache_db.*"
                },
                "properties": [
                  {
                    "id": "color",
                    "value": {
                      "fixedColor": "#2ECC71",
                      "mode": "fixed"
                    }
                  }
                ]
              }
            ]
          },
          "gridPos": {
            "h": 7,
            "w": 12,
            "x": 12,
            "y": 252
          },
          "id": 18,
          "options": {
            "legend": {
              "calcs": [],
              "displayMode": "list",
              "placement": "bottom",
              "showLegend": true
            },
            "tooltip": {
              "hideZeros": false,
              "mode": "multi",
              "sort": "none"
            }
          },
          "pluginVersion": "12.4.2",
          "targets": [
            {
              "expr": "rate(container_sched_wakeup_total{container_role=\"cache_db\"}[1m])",
              "legendFormat": "{{container}} ({{container_role}})",
              "refId": "A"
            }
          ],
          "title": "缓存/数据库类容器线程唤醒频率",
          "type": "timeseries"
        }
      ],
      "title": "缓存/数据库类容器专区",
      "type": "row"
    },
    {
      "collapsed": false,
      "gridPos": {
        "h": 1,
        "w": 24,
        "x": 0,
        "y": 7
      },
      "id": 103,
      "panels": [],
      "title": "IO 模块专区",
      "type": "row"
    },
    {
      "datasource": {
        "type": "prometheus",
        "uid": "PBFA97CFB590B2093"
      },
      "fieldConfig": {
        "defaults": {
          "color": {
            "mode": "thresholds"
          },
          "mappings": [],
          "thresholds": {
            "mode": "absolute",
            "steps": [
              {
                "color": "green",
                "value": 0
              }
            ]
          }
        },
        "overrides": []
      },
      "gridPos": {
        "h": 7,
        "w": 7,
        "x": 0,
        "y": 8
      },
      "id": 110,
      "options": {
        "colorMode": "value",
        "graphMode": "area",
        "justifyMode": "auto",
        "orientation": "auto",
        "percentChangeColorMode": "standard",
        "reduceOptions": {
          "calcs": [
            "lastNotNull"
          ],
          "fields": "",
          "values": false
        },
        "showPercentChange": false,
        "textMode": "name",
        "wideLayout": true
      },
      "pluginVersion": "12.4.2",
      "targets": [
        {
          "editorMode": "code",
          "expr": "topk(1, container_io_stat_rbytes + container_io_stat_wbytes)",
          "legendFormat": "{{container}}",
          "range": true,
          "refId": "A"
        }
      ],
      "title": "IO最繁忙容器",
      "type": "stat"
    },
    {
      "datasource": {
        "type": "prometheus",
        "uid": "PBFA97CFB590B2093"
      },
      "fieldConfig": {
        "defaults": {
          "color": {
            "mode": "thresholds"
          },
          "mappings": [],
          "thresholds": {
            "mode": "absolute",
            "steps": [
              {
                "color": "green",
                "value": 0
              },
              {
                "color": "red",
                "value": 80
              }
            ]
          }
        },
        "overrides": []
      },
      "gridPos": {
        "h": 7,
        "w": 8,
        "x": 7,
        "y": 8
      },
      "id": 111,
      "options": {
        "colorMode": "value",
        "graphMode": "area",
        "justifyMode": "auto",
        "orientation": "auto",
        "percentChangeColorMode": "standard",
        "reduceOptions": {
          "calcs": [
            "lastNotNull"
          ],
          "fields": "",
          "values": false
        },
        "showPercentChange": false,
        "textMode": "name",
        "wideLayout": true
      },
      "pluginVersion": "12.4.2",
      "targets": [
        {
          "editorMode": "code",
          "expr": "topk(1, container_io_latency_avg_us)",
          "legendFormat": "{{container}}",
          "range": true,
          "refId": "A"
        }
      ],
      "title": "IO延迟最高容器",
      "type": "stat"
    },
    {
      "datasource": {
        "type": "prometheus",
        "uid": "PBFA97CFB590B2093"
      },
      "fieldConfig": {
        "defaults": {
          "color": {
            "mode": "thresholds"
          },
          "mappings": [],
          "thresholds": {
            "mode": "absolute",
            "steps": [
              {
                "color": "green",
                "value": 0
              },
              {
                "color": "red",
                "value": 80
              }
            ]
          },
          "unit": "µs"
        },
        "overrides": [
          {
            "matcher": {
              "id": "byRegexp",
              "options": ".*web.*"
            },
            "properties": [
              {
                "id": "color",
                "value": {
                  "fixedColor": "#4c8bf5",
                  "mode": "fixed"
                }
              }
            ]
          },
          {
            "matcher": {
              "id": "byRegexp",
              "options": ".*cache_db.*"
            },
            "properties": [
              {
                "id": "color",
                "value": {
                  "fixedColor": "#2ecc71",
                  "mode": "fixed"
                }
              }
            ]
          }
        ]
      },
      "gridPos": {
        "h": 7,
        "w": 7,
        "x": 15,
        "y": 8
      },
      "id": 112,
      "options": {
        "colorMode": "value",
        "graphMode": "area",
        "justifyMode": "auto",
        "orientation": "auto",
        "percentChangeColorMode": "standard",
        "reduceOptions": {
          "calcs": [
            "lastNotNull"
          ],
          "fields": "",
          "values": false
        },
        "showPercentChange": false,
        "textMode": "value",
        "wideLayout": true
      },
      "pluginVersion": "12.4.2",
      "targets": [
        {
          "editorMode": "code",
          "expr": "topk(1, container_io_latency_avg_us)",
          "legendFormat": "{{container}}",
          "range": true,
          "refId": "A"
        }
      ],
      "title": "IO平均延迟",
      "type": "stat"
    },
    {
      "datasource": {
        "type": "prometheus",
        "uid": "Prometheus"
      },
      "description": "展示容器在 cgroup io.stat 视角下的累计读字节。",
      "fieldConfig": {
        "defaults": {
          "color": {
            "mode": "palette-classic"
          },
          "custom": {
            "axisBorderShow": false,
            "axisCenteredZero": false,
            "axisColorMode": "text",
            "axisLabel": "",
            "axisPlacement": "auto",
            "barAlignment": 0,
            "barWidthFactor": 0.6,
            "drawStyle": "line",
            "fillOpacity": 10,
            "gradientMode": "opacity",
            "hideFrom": {
              "legend": false,
              "tooltip": false,
              "viz": false
            },
            "insertNulls": false,
            "lineInterpolation": "linear",
            "lineWidth": 2,
            "pointSize": 3,
            "scaleDistribution": {
              "type": "linear"
            },
            "showPoints": "never",
            "showValues": false,
            "spanNulls": false,
            "stacking": {
              "group": "A",
              "mode": "none"
            },
            "thresholdsStyle": {
              "mode": "off"
            }
          },
          "mappings": [],
          "thresholds": {
            "mode": "absolute",
            "steps": [
              {
                "color": "green",
                "value": 0
              },
              {
                "color": "red",
                "value": 80
              }
            ]
          },
          "unit": "bytes"
        },
        "overrides": [
          {
            "matcher": {
              "id": "byRegexp",
              "options": ".*web.*"
            },
            "properties": [
              {
                "id": "color",
                "value": {
                  "fixedColor": "#4C8BF5",
                  "mode": "fixed"
                }
              }
            ]
          },
          {
            "matcher": {
              "id": "byRegexp",
              "options": ".*cache_db.*"
            },
            "properties": [
              {
                "id": "color",
                "value": {
                  "fixedColor": "#2ECC71",
                  "mode": "fixed"
                }
              }
            ]
          }
        ]
      },
      "gridPos": {
        "h": 7,
        "w": 12,
        "x": 0,
        "y": 15
      },
      "id": 104,
      "options": {
        "legend": {
          "calcs": [],
          "displayMode": "list",
          "placement": "bottom",
          "showLegend": true
        },
        "tooltip": {
          "hideZeros": false,
          "mode": "multi",
          "sort": "none"
        }
      },
      "pluginVersion": "12.4.2",
      "targets": [
        {
          "expr": "container_io_stat_rbytes",
          "legendFormat": "{{container}} ({{container_role}})",
          "refId": "A"
        }
      ],
      "title": "各容器累计读字节",
      "type": "timeseries"
    },
    {
      "datasource": {
        "type": "prometheus",
        "uid": "Prometheus"
      },
      "description": "展示容器在 cgroup io.stat 视角下的累计写字节。",
      "fieldConfig": {
        "defaults": {
          "color": {
            "mode": "palette-classic"
          },
          "custom": {
            "axisBorderShow": false,
            "axisCenteredZero": false,
            "axisColorMode": "text",
            "axisLabel": "",
            "axisPlacement": "auto",
            "barAlignment": 0,
            "barWidthFactor": 0.6,
            "drawStyle": "line",
            "fillOpacity": 10,
            "gradientMode": "opacity",
            "hideFrom": {
              "legend": false,
              "tooltip": false,
              "viz": false
            },
            "insertNulls": false,
            "lineInterpolation": "linear",
            "lineWidth": 2,
            "pointSize": 3,
            "scaleDistribution": {
              "type": "linear"
            },
            "showPoints": "never",
            "showValues": false,
            "spanNulls": false,
            "stacking": {
              "group": "A",
              "mode": "none"
            },
            "thresholdsStyle": {
              "mode": "off"
            }
          },
          "mappings": [],
          "thresholds": {
            "mode": "absolute",
            "steps": [
              {
                "color": "green",
                "value": 0
              },
              {
                "color": "red",
                "value": 80
              }
            ]
          },
          "unit": "bytes"
        },
        "overrides": [
          {
            "matcher": {
              "id": "byRegexp",
              "options": ".*web.*"
            },
            "properties": [
              {
                "id": "color",
                "value": {
                  "fixedColor": "#4C8BF5",
                  "mode": "fixed"
                }
              }
            ]
          },
          {
            "matcher": {
              "id": "byRegexp",
              "options": ".*cache_db.*"
            },
            "properties": [
              {
                "id": "color",
                "value": {
                  "fixedColor": "#2ECC71",
                  "mode": "fixed"
                }
              }
            ]
          }
        ]
      },
      "gridPos": {
        "h": 7,
        "w": 12,
        "x": 12,
        "y": 15
      },
      "id": 105,
      "options": {
        "legend": {
          "calcs": [],
          "displayMode": "list",
          "placement": "bottom",
          "showLegend": true
        },
        "tooltip": {
          "hideZeros": false,
          "mode": "multi",
          "sort": "none"
        }
      },
      "pluginVersion": "12.4.2",
      "targets": [
        {
          "expr": "container_io_stat_wbytes",
          "legendFormat": "{{container}} ({{container_role}})",
          "refId": "A"
        }
      ],
      "title": "各容器累计写字节",
      "type": "timeseries"
    },
    {
      "datasource": {
        "type": "prometheus",
        "uid": "Prometheus"
      },
      "description": "展示当前窗口内容器 IO 平均延迟。",
      "fieldConfig": {
        "defaults": {
          "color": {
            "mode": "palette-classic"
          },
          "custom": {
            "axisBorderShow": false,
            "axisCenteredZero": false,
            "axisColorMode": "text",
            "axisLabel": "",
            "axisPlacement": "auto",
            "barAlignment": 0,
            "barWidthFactor": 0.6,
            "drawStyle": "line",
            "fillOpacity": 10,
            "gradientMode": "opacity",
            "hideFrom": {
              "legend": false,
              "tooltip": false,
              "viz": false
            },
            "insertNulls": false,
            "lineInterpolation": "linear",
            "lineWidth": 2,
            "pointSize": 3,
            "scaleDistribution": {
              "type": "linear"
            },
            "showPoints": "never",
            "showValues": false,
            "spanNulls": false,
            "stacking": {
              "group": "A",
              "mode": "none"
            },
            "thresholdsStyle": {
              "mode": "off"
            }
          },
          "mappings": [],
          "thresholds": {
            "mode": "absolute",
            "steps": [
              {
                "color": "green",
                "value": 0
              },
              {
                "color": "red",
                "value": 80
              }
            ]
          },
          "unit": "µs"
        },
        "overrides": [
          {
            "matcher": {
              "id": "byRegexp",
              "options": ".*web.*"
            },
            "properties": [
              {
                "id": "color",
                "value": {
                  "fixedColor": "#4C8BF5",
                  "mode": "fixed"
                }
              }
            ]
          },
          {
            "matcher": {
              "id": "byRegexp",
              "options": ".*cache_db.*"
            },
            "properties": [
              {
                "id": "color",
                "value": {
                  "fixedColor": "#2ECC71",
                  "mode": "fixed"
                }
              }
            ]
          }
        ]
      },
      "gridPos": {
        "h": 7,
        "w": 12,
        "x": 0,
        "y": 22
      },
      "id": 106,
      "options": {
        "legend": {
          "calcs": [],
          "displayMode": "list",
          "placement": "bottom",
          "showLegend": true
        },
        "tooltip": {
          "hideZeros": false,
          "mode": "multi",
          "sort": "none"
        }
      },
      "pluginVersion": "12.4.2",
      "targets": [
        {
          "expr": "container_io_latency_avg_us",
          "legendFormat": "{{container}} ({{container_role}})",
          "refId": "A"
        }
      ],
      "title": "各容器当前窗口平均 IO 延迟",
      "type": "timeseries"
    },
    {
      "datasource": {
        "type": "prometheus",
        "uid": "Prometheus"
      },
      "description": "展示当前窗口内容器 IO 最大延迟。",
      "fieldConfig": {
        "defaults": {
          "color": {
            "mode": "palette-classic"
          },
          "custom": {
            "axisBorderShow": false,
            "axisCenteredZero": false,
            "axisColorMode": "text",
            "axisLabel": "",
            "axisPlacement": "auto",
            "barAlignment": 0,
            "barWidthFactor": 0.6,
            "drawStyle": "line",
            "fillOpacity": 10,
            "gradientMode": "opacity",
            "hideFrom": {
              "legend": false,
              "tooltip": false,
              "viz": false
            },
            "insertNulls": false,
            "lineInterpolation": "linear",
            "lineWidth": 2,
            "pointSize": 3,
            "scaleDistribution": {
              "type": "linear"
            },
            "showPoints": "never",
            "showValues": false,
            "spanNulls": false,
            "stacking": {
              "group": "A",
              "mode": "none"
            },
            "thresholdsStyle": {
              "mode": "off"
            }
          },
          "mappings": [],
          "thresholds": {
            "mode": "absolute",
            "steps": [
              {
                "color": "green",
                "value": 0
              },
              {
                "color": "red",
                "value": 80
              }
            ]
          },
          "unit": "µs"
        },
        "overrides": [
          {
            "matcher": {
              "id": "byRegexp",
              "options": ".*web.*"
            },
            "properties": [
              {
                "id": "color",
                "value": {
                  "fixedColor": "#4C8BF5",
                  "mode": "fixed"
                }
              }
            ]
          },
          {
            "matcher": {
              "id": "byRegexp",
              "options": ".*cache_db.*"
            },
            "properties": [
              {
                "id": "color",
                "value": {
                  "fixedColor": "#2ECC71",
                  "mode": "fixed"
                }
              }
            ]
          }
        ]
      },
      "gridPos": {
        "h": 7,
        "w": 12,
        "x": 12,
        "y": 22
      },
      "id": 107,
      "options": {
        "legend": {
          "calcs": [],
          "displayMode": "list",
          "placement": "bottom",
          "showLegend": true
        },
        "tooltip": {
          "hideZeros": false,
          "mode": "multi",
          "sort": "none"
        }
      },
      "pluginVersion": "12.4.2",
      "targets": [
        {
          "expr": "container_io_latency_max_us",
          "legendFormat": "{{container}} ({{container_role}})",
          "refId": "A"
        }
      ],
      "title": "各容器当前窗口最大 IO 延迟",
      "type": "timeseries"
    },
    {
      "datasource": {
        "type": "prometheus",
        "uid": "Prometheus"
      },
      "description": "仅展示 Web 类容器的累计读字节。",
      "fieldConfig": {
        "defaults": {
          "color": {
            "mode": "palette-classic"
          },
          "custom": {
            "axisBorderShow": false,
            "axisCenteredZero": false,
            "axisColorMode": "text",
            "axisLabel": "",
            "axisPlacement": "auto",
            "barAlignment": 0,
            "barWidthFactor": 0.6,
            "drawStyle": "line",
            "fillOpacity": 10,
            "gradientMode": "opacity",
            "hideFrom": {
              "legend": false,
              "tooltip": false,
              "viz": false
            },
            "insertNulls": false,
            "lineInterpolation": "linear",
            "lineWidth": 2,
            "pointSize": 3,
            "scaleDistribution": {
              "type": "linear"
            },
            "showPoints": "never",
            "showValues": false,
            "spanNulls": false,
            "stacking": {
              "group": "A",
              "mode": "none"
            },
            "thresholdsStyle": {
              "mode": "off"
            }
          },
          "mappings": [],
          "thresholds": {
            "mode": "absolute",
            "steps": [
              {
                "color": "green",
                "value": 0
              },
              {
                "color": "red",
                "value": 80
              }
            ]
          },
          "unit": "bytes"
        },
        "overrides": [
          {
            "matcher": {
              "id": "byRegexp",
              "options": ".*web.*"
            },
            "properties": [
              {
                "id": "color",
                "value": {
                  "fixedColor": "#4C8BF5",
                  "mode": "fixed"
                }
              }
            ]
          },
          {
            "matcher": {
              "id": "byRegexp",
              "options": ".*cache_db.*"
            },
            "properties": [
              {
                "id": "color",
                "value": {
                  "fixedColor": "#2ECC71",
                  "mode": "fixed"
                }
              }
            ]
          }
        ]
      },
      "gridPos": {
        "h": 7,
        "w": 12,
        "x": 0,
        "y": 29
      },
      "id": 108,
      "options": {
        "legend": {
          "calcs": [],
          "displayMode": "list",
          "placement": "bottom",
          "showLegend": true
        },
        "tooltip": {
          "hideZeros": false,
          "mode": "multi",
          "sort": "none"
        }
      },
      "pluginVersion": "12.4.2",
      "targets": [
        {
          "expr": "container_io_stat_rbytes{container_role=\"web\"}",
          "legendFormat": "{{container}} ({{container_role}})",
          "refId": "A"
        }
      ],
      "title": "Web 类容器累计读字节",
      "type": "timeseries"
    },
    {
      "datasource": {
        "type": "prometheus",
        "uid": "Prometheus"
      },
      "description": "仅展示缓存/数据库类容器的累计写字节。",
      "fieldConfig": {
        "defaults": {
          "color": {
            "mode": "palette-classic"
          },
          "custom": {
            "axisBorderShow": false,
            "axisCenteredZero": false,
            "axisColorMode": "text",
            "axisLabel": "",
            "axisPlacement": "auto",
            "barAlignment": 0,
            "barWidthFactor": 0.6,
            "drawStyle": "line",
            "fillOpacity": 10,
            "gradientMode": "opacity",
            "hideFrom": {
              "legend": false,
              "tooltip": false,
              "viz": false
            },
            "insertNulls": false,
            "lineInterpolation": "linear",
            "lineWidth": 2,
            "pointSize": 3,
            "scaleDistribution": {
              "type": "linear"
            },
            "showPoints": "never",
            "showValues": false,
            "spanNulls": false,
            "stacking": {
              "group": "A",
              "mode": "none"
            },
            "thresholdsStyle": {
              "mode": "off"
            }
          },
          "mappings": [],
          "thresholds": {
            "mode": "absolute",
            "steps": [
              {
                "color": "green",
                "value": 0
              },
              {
                "color": "red",
                "value": 80
              }
            ]
          },
          "unit": "bytes"
        },
        "overrides": [
          {
            "matcher": {
              "id": "byRegexp",
              "options": ".*web.*"
            },
            "properties": [
              {
                "id": "color",
                "value": {
                  "fixedColor": "#4C8BF5",
                  "mode": "fixed"
                }
              }
            ]
          },
          {
            "matcher": {
              "id": "byRegexp",
              "options": ".*cache_db.*"
            },
            "properties": [
              {
                "id": "color",
                "value": {
                  "fixedColor": "#2ECC71",
                  "mode": "fixed"
                }
              }
            ]
          }
        ]
      },
      "gridPos": {
        "h": 7,
        "w": 12,
        "x": 12,
        "y": 29
      },
      "id": 109,
      "options": {
        "legend": {
          "calcs": [],
          "displayMode": "list",
          "placement": "bottom",
          "showLegend": true
        },
        "tooltip": {
          "hideZeros": false,
          "mode": "multi",
          "sort": "none"
        }
      },
      "pluginVersion": "12.4.2",
      "targets": [
        {
          "expr": "container_io_stat_wbytes{container_role=\"cache_db\"}",
          "legendFormat": "{{container}} ({{container_role}})",
          "refId": "A"
        }
      ],
      "title": "缓存/数据库类容器累计写字节",
      "type": "timeseries"
    }
  ],
  "preload": false,
  "refresh": "5s",
  "schemaVersion": 42,
  "tags": [
    "ebpf",
    "container",
    "monitor",
    "classified"
  ],
  "templating": {
    "list": []
  },
  "time": {
    "from": "now-15m",
    "to": "now"
  },
  "timepicker": {},
  "timezone": "browser",
  "title": "Container Classified Monitor FINAL",
  "uid": "container-classified-final",
  "version": 2,
  "weekStart": ""
}
